{
  "_links": {
    "self": {
      "href": "http:\/\/local.alshaya.com\/en\/block\/2?_format=hal_json"
    },
    "type": {
      "href": "http:\/\/drupal.org\/rest\/type\/block_content\/basic"
    },
    "http:\/\/drupal.org\/rest\/relation\/block_content\/basic\/content_translation_uid": [
      {
        "href": "http:\/\/local.alshaya.com\/en\/user\/0?_format=hal_json",
        "lang": "en"
      }
    ]
  },
  "id": [
    {
      "value": "2"
    }
  ],
  "uuid": [
    {
      "value": "1a2425f6-8986-4e40-a30a-88ffebf18c53"
    }
  ],
  "revision_id": [
    {
      "value": "2"
    }
  ],
  "langcode": [
    {
      "value": "en",
      "lang": "en"
    }
  ],
  "type": [
    {
      "target_id": "basic"
    }
  ],
  "info": [
    {
      "value": "You\u2019ll be able to",
      "lang": "en"
    }
  ],
  "changed": [
    {
      "value": "1491284697",
      "lang": "en"
    }
  ],
  "revision_created": [
    {
      "value": "1490641146"
    }
  ],
  "revision_translation_affected": [
    {
      "value": "1",
      "lang": "en"
    }
  ],
  "default_langcode": [
    {
      "value": "1",
      "lang": "en"
    }
  ],
  "content_translation_source": [
    {
      "value": "und",
      "lang": "en"
    }
  ],
  "content_translation_outdated": [
    {
      "value": "0",
      "lang": "en"
    }
  ],
  "_embedded": {
    "http:\/\/drupal.org\/rest\/relation\/block_content\/basic\/content_translation_uid": [
      {
        "_links": {
          "self": {
            "href": "http:\/\/local.alshaya.com\/en\/user\/0?_format=hal_json"
          },
          "type": {
            "href": "http:\/\/drupal.org\/rest\/type\/user\/user"
          }
        },
        "uuid": [
          {
            "value": "fa56033a-bf5f-4528-9057-6c2b5fd94fbb"
          }
        ],
        "lang": "en"
      }
    ]
  },
  "content_translation_status": [
    {
      "value": "1",
      "lang": "en"
    }
  ],
  "content_translation_created": [
    {
      "value": "1491243645",
      "lang": "en"
    }
  ],
  "body": [
    {
      "value": "<p><i class=\"icon-wish\"><\/i>save items to your wishlist<\/p>\r\n<p><i class=\"icon-store\"><\/i>store multiple shipping addresses<\/p>\r\n<p><i class=\"icon-offer\"><\/i>get special offers and updates on deals<\/p>\r\n<p><a href=\"\">already registered? sign in here<\/a><\/p>",
      "format": "rich_text",
      "summary": "",
      "lang": "en"
    }
  ]
}